{"data":{"ArrivalBoard":{"generatedAt":"2025-09-30T19:31:38.5448201+01:00","nrccMessages":null,"departureStation":{"locationName":"Cardiff Central","crs":"CDF","via":null},"filterStation":null,"services":[{"rid":"202509308008254","trainUid":"P08254","serviceType":{"mode":"Train","category":"ExpressPassengerTrain"},"origin":[{"locationName":"London Paddington","crs":"PAD","via":null}],"destination":[{"locationName":"Swansea","crs":"SWA","via":null}],"journeyDetails":{"from":{"locationName":"London Paddington","crs":"PAD","via":null},"to":{"locationName":"Cardiff Central","crs":"CDF","via":null},"stops":6,"departureInfo":{"scheduled":"2025-09-30T17:18:00+01:00","estimated":null,"actual":"2025-09-30T17:21:09+01:00"},"arrivalInfo":{"scheduled":"2025-09-30T19:10:00+01:00","estimated":"2025-09-30T19:35:48+01:00","actual":null}},"operator":{"name":"Great Western Railway","code":"GW"},"status":{"status":"Late","delayReason":"This train has been delayed by congestion","cancelReason":null},"departureInfo":{"scheduled":"2025-09-30T19:18:00+01:00","estimated":"2025-09-30T19:36:48+01:00","actual":null},"arrivalInfo":{"scheduled":"2025-09-30T19:10:00+01:00","estimated":"2025-09-30T19:35:48+01:00","actual":null},"platform":"3","loadingLevel":"Unknown"},{"rid":"202509307156026","trainUid":"G56026","serviceType":{"mode":"Train","category":"ExpressPassengerTrain"},"origin":[{"locationName":"Holyhead","crs":"HHD","via":null}],"destination":[{"locationName":"Cardiff Central","crs":"CDF","via":null}],"journeyDetails":{"from":{"locationName":"Holyhead","crs":"HHD","via":null},"to":{"locationName":"Cardiff Central","crs":"CDF","via":null},"stops":26,"departureInfo":{"scheduled":"2025-09-30T14:30:00+01:00","estimated":null,"actual":"2025-09-30T14:30:00+01:00"},"arrivalInfo":{"scheduled":"2025-09-30T19:20:00+01:00","estimated":null,"actual":"2025-09-30T19:30:52+01:00"}},"operator":{"name":"Transport for Wales","code":"AW"},"status":{"status":"Late","delayReason":null,"cancelReason":null},"departureInfo":null,"arrivalInfo":{"scheduled":"2025-09-30T19:20:00+01:00","estimated":null,"actual":"2025-09-30T19:30:52+01:00"},"platform":"2","loadingLevel":"Unknown"},{"rid":"202509308009876","trainUid":"P09876","serviceType":{"mode":"Train","category":"PassengerTrain"},"origin":[{"locationName":"Taunton","crs":"TAU","via":null}],"destination":[{"locationName":"Cardiff Central","crs":"CDF","via":null}],"journeyDetails":{"from":{"locationName":"Taunton","crs":"TAU","via":null},"to":{"locationName":"Cardiff Central","crs":"CDF","via":null},"stops":17,"departureInfo":{"scheduled":"2025-09-30T17:10:00+01:00","estimated":null,"actual":"2025-09-30T17:09:46+01:00"},"arrivalInfo":{"scheduled":"2025-09-30T19:25:00+01:00","estimated":"2025-09-30T19:32:30+01:00","actual":null}},"operator":{"name":"Great Western Railway","code":"GW"},"status":{"status":"Late","delayReason":"This train has been delayed by animals on the railway","cancelReason":null},"departureInfo":null,"arrivalInfo":{"scheduled":"2025-09-30T19:25:00+01:00","estimated":"2025-09-30T19:32:30+01:00","actual":null},"platform":"3","loadingLevel":"Unknown"},{"rid":"202509307155907","trainUid":"G55907","serviceType":{"mode":"Train","category":"ExpressPassengerTrain"},"origin":[{"locationName":"Aberdare","crs":"ABA","via":null}],"destination":[{"locationName":"Merthyr Tydfil","crs":"MER","via":null}],"journeyDetails":{"from":{"locationName":"Aberdare","crs":"ABA","via":null},"to":{"locationName":"Cardiff Central","crs":"CDF","via":null},"stops":15,"departureInfo":{"scheduled":"2025-09-30T18:22:00+01:00","estimated":null,"actual":"2025-09-30T18:21:58+01:00"},"arrivalInfo":{"scheduled":"2025-09-30T19:26:00+01:00","estimated":null,"actual":"2025-09-30T19:28:10+01:00"}},"operator":{"name":"Transport for Wales","code":"AW"},"status":{"status":"Late","delayReason":null,"cancelReason":null},"departureInfo":{"scheduled":"2025-09-30T19:30:00+01:00","estimated":null,"actual":"2025-09-30T19:30:55+01:00"},"arrivalInfo":{"scheduled":"2025-09-30T19:26:00+01:00","estimated":null,"actual":"2025-09-30T19:28:10+01:00"},"platform":"6","loadingLevel":"Unknown"},{"rid":"202509307156912","trainUid":"G56912","serviceType":{"mode":"Train","category":"PassengerTrain"},"origin":[{"locationName":"Bargoed","crs":"BGD","via":null}],"destination":[{"locationName":"Cardiff Central","crs":"CDF","via":null}],"journeyDetails":{"from":{"locationName":"Bargoed","crs":"BGD","via":null},"to":{"locationName":"Cardiff Central","crs":"CDF","via":null},"stops":12,"departureInfo":{"scheduled":"2025-09-30T18:43:00+01:00","estimated":null,"actual":"2025-09-30T18:43:17+01:00"},"arrivalInfo":{"scheduled":"2025-09-30T19:28:00+01:00","estimated":null,"actual":"2025-09-30T19:29:51+01:00"}},"operator":{"name":"Transport for Wales","code":"AW"},"status":{"status":"Late","delayReason":null,"cancelReason":null},"departureInfo":null,"arrivalInfo":{"scheduled":"2025-09-30T19:28:00+01:00","estimated":null,"actual":"2025-09-30T19:29:51+01:00"},"platform":"8","loadingLevel":"Unknown"},{"rid":"202509307157614","trainUid":"G57614","serviceType":{"mode":"Train","category":"PassengerTrain"},"origin":[{"locationName":"Coryton","crs":"COY","via":null}],"destination":[{"locationName":"Penarth","crs":"PEN","via":null}],"journeyDetails":{"from":{"locationName":"Coryton","crs":"COY","via":null},"to":{"locationName":"Cardiff Central","crs":"CDF","via":null},"stops":6,"departureInfo":{"scheduled":"2025-09-30T19:12:00+01:00","estimated":null,"actual":"2025-09-30T19:12:00+01:00"},"arrivalInfo":{"scheduled":"2025-09-30T19:34:00+01:00","estimated":null,"actual":"2025-09-30T19:31:52+01:00"}},"operator":{"name":"Transport for Wales","code":"AW"},"status":{"status":"OnTime","delayReason":null,"cancelReason":null},"departureInfo":{"scheduled":"2025-09-30T19:35:00+01:00","estimated":"2025-09-30T19:35:00+01:00","actual":null},"arrivalInfo":{"scheduled":"2025-09-30T19:34:00+01:00","estimated":null,"actual":"2025-09-30T19:31:52+01:00"},"platform":"7","loadingLevel":"Unknown"},{"rid":"202509308008255","trainUid":"P08255","serviceType":{"mode":"Train","category":"ExpressPassengerTrain"},"origin":[{"locationName":"London Paddington","crs":"PAD","via":null}],"destination":[{"locationName":"Carmarthen","crs":"CMN","via":null}],"journeyDetails":{"from":{"locationName":"London Paddington","crs":"PAD","via":null},"to":{"locationName":"Cardiff Central","crs":"CDF","via":null},"stops":5,"departureInfo":{"scheduled":"2025-09-30T17:48:00+01:00","estimated":null,"actual":"2025-09-30T17:47:40+01:00"},"arrivalInfo":{"scheduled":"2025-09-30T19:36:00+01:00","estimated":"2025-09-30T19:45:03+01:00","actual":null}},"operator":{"name":"Great Western Railway","code":"GW"},"status":{"status":"Late","delayReason":"This train has been delayed by congestion","cancelReason":null},"departureInfo":{"scheduled":"2025-09-30T19:39:00+01:00","estimated":"2025-09-30T19:46:03+01:00","actual":null},"arrivalInfo":{"scheduled":"2025-09-30T19:36:00+01:00","estimated":"2025-09-30T19:45:03+01:00","actual":null},"platform":"3","loadingLevel":"Unknown"},{"rid":"202509307156758","trainUid":"G56758","serviceType":{"mode":"Train","category":"PassengerTrain"},"origin":[{"locationName":"Rhymney","crs":"RHY","via":null}],"destination":[{"locationName":"Bridgend","crs":"BGN","via":"via Rhoose Cardiff Int Airport"}],"journeyDetails":{"from":{"locationName":"Rhymney","crs":"RHY","via":null},"to":{"locationName":"Cardiff Central","crs":"CDF","via":null},"stops":12,"departureInfo":{"scheduled":"2025-09-30T18:44:00+01:00","estimated":null,"actual":"2025-09-30T18:44:58+01:00"},"arrivalInfo":{"scheduled":"2025-09-30T19:38:00+01:00","estimated":"2025-09-30T19:38:00+01:00","actual":null}},"operator":{"name":"Transport for Wales","code":"AW"},"status":{"status":"OnTime","delayReason":null,"cancelReason":null},"departureInfo":{"scheduled":"2025-09-30T19:39:00+01:00","estimated":"2025-09-30T19:39:00+01:00","actual":null},"arrivalInfo":{"scheduled":"2025-09-30T19:38:00+01:00","estimated":"2025-09-30T19:38:00+01:00","actual":null},"platform":"7","loadingLevel":"Unknown"},{"rid":"202509307156347","trainUid":"G56347","serviceType":{"mode":"Train","category":"PassengerTrain"},"origin":[{"locationName":"Swansea","crs":"SWA","via":null}],"destination":[{"locationName":"Cardiff Central","crs":"CDF","via":null}],"journeyDetails":{"from":{"locationName":"Swansea","crs":"SWA","via":null},"to":{"locationName":"Cardiff Central","crs":"CDF","via":null},"stops":12,"departureInfo":{"scheduled":"2025-09-30T18:28:00+01:00","estimated":null,"actual":"2025-09-30T18:28:26+01:00"},"arrivalInfo":{"scheduled":"2025-09-30T19:40:00+01:00","estimated":"2025-09-30T19:44:10+01:00","actual":null}},"operator":{"name":"Transport for Wales","code":"AW"},"status":{"status":"Late","delayReason":null,"cancelReason":null},"departureInfo":null,"arrivalInfo":{"scheduled":"2025-09-30T19:40:00+01:00","estimated":"2025-09-30T19:44:10+01:00","actual":null},"platform":"0","loadingLevel":"Unknown"},{"rid":"202509307157800","trainUid":"G57800","serviceType":{"mode":"Train","category":"PassengerTrain"},"origin":[{"locationName":"Bridgend","crs":"BGN","via":null}],"destination":[{"locationName":"Rhymney","crs":"RHY","via":null}],"journeyDetails":{"from":{"locationName":"Bridgend","crs":"BGN","via":null},"to":{"locationName":"Cardiff Central","crs":"CDF","via":null},"stops":10,"departureInfo":{"scheduled":"2025-09-30T18:40:00+01:00","estimated":null,"actual":"2025-09-30T18:39:06+01:00"},"arrivalInfo":{"scheduled":"2025-09-30T19:41:00+01:00","estimated":"2025-09-30T19:41:00+01:00","actual":null}},"operator":{"name":"Transport for Wales","code":"AW"},"status":{"status":"OnTime","delayReason":null,"cancelReason":null},"departureInfo":{"scheduled":"2025-09-30T19:41:00+01:00","estimated":"2025-09-30T19:41:00+01:00","actual":null},"arrivalInfo":{"scheduled":"2025-09-30T19:41:00+01:00","estimated":"2025-09-30T19:41:00+01:00","actual":null},"platform":"6","loadingLevel":"Unknown"}]}}}
