{"data":{"ArrivalBoard":{"generatedAt":"2025-03-23T14:18:03.437004+00:00","nrccMessages":null,"departureStation":{"locationName":"Cardiff Central","crs":"CDF","via":null},"filterStation":null,"services":[{"rid":"202503238719106","trainUid":"W19106","serviceType":{"mode":"Train","category":"ExpressPassengerTrain"},"origin":[{"locationName":"Manchester Piccadilly","crs":"MAN","via":null}],"destination":[{"locationName":"Swansea","crs":"SWA","via":null}],"journeyDetails":{"from":{"locationName":"Manchester Piccadilly","crs":"MAN","via":null},"to":{"locationName":"Cardiff Central","crs":"CDF","via":null},"stops":12,"departureInfo":{"scheduled":"2025-03-23T10:30:00+00:00","estimated":null,"actual":"2025-03-23T10:30:20+00:00"},"arrivalInfo":{"scheduled":"2025-03-23T13:48:00+00:00","estimated":null,"actual":"2025-03-23T13:52:45+00:00"}},"operator":{"name":"Transport for Wales","code":"AW"},"status":{"status":"Late","delayReason":"This train has been delayed by a speed restriction","cancelReason":null},"departureInfo":{"scheduled":"2025-03-23T14:12:00+00:00","estimated":null,"actual":null},"arrivalInfo":{"scheduled":"2025-03-23T13:48:00+00:00","estimated":null,"actual":"2025-03-23T13:52:45+00:00"},"platform":"3A","loadingLevel":"Unknown"},{"rid":"202503237145765","trainUid":"G45765","serviceType":{"mode":"Train","category":"ExpressPassengerTrain"},"origin":[{"locationName":"Swansea","crs":"SWA","via":null}],"destination":[{"locationName":"London Paddington","crs":"PAD","via":null}],"journeyDetails":{"from":{"locationName":"Swansea","crs":"SWA","via":null},"to":{"locationName":"Cardiff Central","crs":"CDF","via":null},"stops":4,"departureInfo":{"scheduled":"2025-03-23T13:23:00+00:00","estimated":"2025-03-23T13:23:00+00:00","actual":null},"arrivalInfo":{"scheduled":"2025-03-23T14:16:00+00:00","estimated":null,"actual":null}},"operator":{"name":"Great Western Railway","code":"GW"},"status":{"status":"Cancelled","delayReason":null,"cancelReason":"This train has been cancelled because of engineering works not being finished on time"},"departureInfo":null,"arrivalInfo":{"scheduled":"2025-03-23T14:16:00+00:00","estimated":null,"actual":null},"platform":"1","loadingLevel":"Unknown"},{"rid":"202503238718581","trainUid":"W18581","serviceType":{"mode":"Train","category":"PassengerTrain"},"origin":[{"locationName":"Barry Island","crs":"BYI","via":null}],"destination":[{"locationName":"Caerphilly","crs":"CPH","via":null}],"journeyDetails":{"from":{"locationName":"Barry Island","crs":"BYI","via":null},"to":{"locationName":"Cardiff Central","crs":"CDF","via":null},"stops":8,"departureInfo":{"scheduled":"2025-03-23T13:49:00+00:00","estimated":null,"actual":"2025-03-23T13:49:17+00:00"},"arrivalInfo":{"scheduled":"2025-03-23T14:21:00+00:00","estimated":null,"actual":"2025-03-23T14:18:05+00:00"}},"operator":{"name":"Transport for Wales","code":"AW"},"status":{"status":"OnTime","delayReason":null,"cancelReason":null},"departureInfo":{"scheduled":"2025-03-23T14:22:00+00:00","estimated":"2025-03-23T14:22:00+00:00","actual":null},"arrivalInfo":{"scheduled":"2025-03-23T14:21:00+00:00","estimated":null,"actual":"2025-03-23T14:18:05+00:00"},"platform":"7B","loadingLevel":"Unknown"},{"rid":"202503238011989","trainUid":"P11989","serviceType":{"mode":"Train","category":"ExpressPassengerTrain"},"origin":[{"locationName":"Derby","crs":"DBY","via":null}],"destination":[{"locationName":"Cardiff Central","crs":"CDF","via":null}],"journeyDetails":{"from":{"locationName":"Derby","crs":"DBY","via":null},"to":{"locationName":"Cardiff Central","crs":"CDF","via":null},"stops":9,"departureInfo":{"scheduled":"2025-03-23T11:40:00+00:00","estimated":"2025-03-23T11:40:00+00:00","actual":null},"arrivalInfo":{"scheduled":"2025-03-23T14:25:00+00:00","estimated":null,"actual":null}},"operator":{"name":"CrossCountry","code":"XC"},"status":{"status":"Cancelled","delayReason":null,"cancelReason":"This train has been cancelled because of a shortage of train drivers"},"departureInfo":null,"arrivalInfo":{"scheduled":"2025-03-23T14:25:00+00:00","estimated":null,"actual":null},"platform":"3A","loadingLevel":"Unknown"},{"rid":"202503238719283","trainUid":"W19283","serviceType":{"mode":"Train","category":"PassengerTrain"},"origin":[{"locationName":"Caerphilly","crs":"CPH","via":null}],"destination":[{"locationName":"Barry Island","crs":"BYI","via":null}],"journeyDetails":{"from":{"locationName":"Caerphilly","crs":"CPH","via":null},"to":{"locationName":"Cardiff Central","crs":"CDF","via":null},"stops":5,"departureInfo":{"scheduled":"2025-03-23T14:09:00+00:00","estimated":null,"actual":"2025-03-23T14:09:09+00:00"},"arrivalInfo":{"scheduled":"2025-03-23T14:28:00+00:00","estimated":"2025-03-23T14:28:00+00:00","actual":null}},"operator":{"name":"Transport for Wales","code":"AW"},"status":{"status":"OnTime","delayReason":null,"cancelReason":null},"departureInfo":{"scheduled":"2025-03-23T14:29:00+00:00","estimated":"2025-03-23T14:29:00+00:00","actual":null},"arrivalInfo":{"scheduled":"2025-03-23T14:28:00+00:00","estimated":"2025-03-23T14:28:00+00:00","actual":null},"platform":"8","loadingLevel":"Unknown"},{"rid":"202503238717541","trainUid":"W17541","serviceType":{"mode":"Train","category":"PassengerTrain"},"origin":[{"locationName":"Cardiff Queen Street","crs":"CDQ","via":null}],"destination":[{"locationName":"Penarth","crs":"PEN","via":null}],"journeyDetails":{"from":{"locationName":"Cardiff Queen Street","crs":"CDQ","via":null},"to":{"locationName":"Cardiff Central","crs":"CDF","via":null},"stops":1,"departureInfo":{"scheduled":"2025-03-23T14:29:00+00:00","estimated":"2025-03-23T14:29:00+00:00","actual":null},"arrivalInfo":{"scheduled":"2025-03-23T14:33:00+00:00","estimated":"2025-03-23T14:33:00+00:00","actual":null}},"operator":{"name":"Transport for Wales","code":"AW"},"status":{"status":"OnTime","delayReason":null,"cancelReason":null},"departureInfo":{"scheduled":"2025-03-23T14:35:00+00:00","estimated":"2025-03-23T14:35:00+00:00","actual":null},"arrivalInfo":{"scheduled":"2025-03-23T14:33:00+00:00","estimated":"2025-03-23T14:33:00+00:00","actual":null},"platform":"8","loadingLevel":"Unknown"},{"rid":"202503237145644","trainUid":"G45644","serviceType":{"mode":"Train","category":"ExpressPassengerTrain"},"origin":[{"locationName":"London Paddington","crs":"PAD","via":null}],"destination":[{"locationName":"Swansea","crs":"SWA","via":null}],"journeyDetails":{"from":{"locationName":"London Paddington","crs":"PAD","via":null},"to":{"locationName":"Cardiff Central","crs":"CDF","via":null},"stops":6,"departureInfo":{"scheduled":"2025-03-23T11:37:00+00:00","estimated":null,"actual":"2025-03-23T11:55:08+00:00"},"arrivalInfo":{"scheduled":"2025-03-23T14:34:00+00:00","estimated":"2025-03-23T14:48:01+00:00","actual":null}},"operator":{"name":"Great Western Railway","code":"GW"},"status":{"status":"Late","delayReason":"This train has been delayed by a passenger being taken ill on a train","cancelReason":null},"departureInfo":{"scheduled":"2025-03-23T14:36:00+00:00","estimated":"2025-03-23T14:49:01+00:00","actual":null},"arrivalInfo":{"scheduled":"2025-03-23T14:34:00+00:00","estimated":"2025-03-23T14:48:01+00:00","actual":null},"platform":"3","loadingLevel":"Unknown"},{"rid":"202503238718704","trainUid":"W18704","serviceType":{"mode":"Train","category":"PassengerTrain"},"origin":[{"locationName":"Bridgend","crs":"BGN","via":null}],"destination":[{"locationName":"Cardiff Central","crs":"CDF","via":null}],"journeyDetails":{"from":{"locationName":"Bridgend","crs":"BGN","via":null},"to":{"locationName":"Cardiff Central","crs":"CDF","via":null},"stops":10,"departureInfo":{"scheduled":"2025-03-23T13:38:00+00:00","estimated":null,"actual":"2025-03-23T13:37:23+00:00"},"arrivalInfo":{"scheduled":"2025-03-23T14:36:00+00:00","estimated":"2025-03-23T14:36:00+00:00","actual":null}},"operator":{"name":"Transport for Wales","code":"AW"},"status":{"status":"OnTime","delayReason":null,"cancelReason":null},"departureInfo":null,"arrivalInfo":{"scheduled":"2025-03-23T14:36:00+00:00","estimated":"2025-03-23T14:36:00+00:00","actual":null},"platform":"6","loadingLevel":"Unknown"},{"rid":"202503237145731","trainUid":"G45731","serviceType":{"mode":"Train","category":"ExpressPassengerTrain"},"origin":[{"locationName":"Salisbury","crs":"SAL","via":null}],"destination":[{"locationName":"Cardiff Central","crs":"CDF","via":null}],"journeyDetails":{"from":{"locationName":"Salisbury","crs":"SAL","via":null},"to":{"locationName":"Cardiff Central","crs":"CDF","via":null},"stops":12,"departureInfo":{"scheduled":"2025-03-23T12:27:00+00:00","estimated":null,"actual":"2025-03-23T12:27:33+00:00"},"arrivalInfo":{"scheduled":"2025-03-23T14:41:00+00:00","estimated":"2025-03-23T14:41:00+00:00","actual":null}},"operator":{"name":"Great Western Railway","code":"GW"},"status":{"status":"OnTime","delayReason":null,"cancelReason":null},"departureInfo":null,"arrivalInfo":{"scheduled":"2025-03-23T14:41:00+00:00","estimated":"2025-03-23T14:41:00+00:00","actual":null},"platform":"3A","loadingLevel":"Unknown"},{"rid":"202503238719301","trainUid":"W19301","serviceType":{"mode":"Train","category":"PassengerTrain"},"origin":[{"locationName":"Merthyr Tydfil","crs":"MER","via":null}],"destination":[{"locationName":"Cardiff Central","crs":"CDF","via":null}],"journeyDetails":{"from":{"locationName":"Merthyr Tydfil","crs":"MER","via":null},"to":{"locationName":"Cardiff Central","crs":"CDF","via":null},"stops":14,"departureInfo":{"scheduled":"2025-03-23T13:39:00+00:00","estimated":null,"actual":"2025-03-23T13:38:59+00:00"},"arrivalInfo":{"scheduled":"2025-03-23T14:41:00+00:00","estimated":"2025-03-23T14:41:00+00:00","actual":null}},"operator":{"name":"Transport for Wales","code":"AW"},"status":{"status":"OnTime","delayReason":null,"cancelReason":null},"departureInfo":null,"arrivalInfo":{"scheduled":"2025-03-23T14:41:00+00:00","estimated":"2025-03-23T14:41:00+00:00","actual":null},"platform":null,"loadingLevel":"Unknown"}]}}}
