{"data":{"ArrivalBoard":{"generatedAt":"2025-02-24T10:23:44.7359477+00:00","nrccMessages":[{"message":"Trains between Pontypridd and Treherbert may be cancelled or revised. More details can be found in <a href=\"https://www.nationalrail.co.uk/service-disruptions/fernhill-20250223/\">Status and Disruptions. </a>","severity":"Minor"}],"departureStation":{"locationName":"Cardiff Central","crs":"CDF","via":null},"filterStation":null,"services":[{"rid":"202502248923545","trainUid":"Y23545","serviceType":{"mode":"Train","category":"PassengerTrain"},"origin":[{"locationName":"Taunton","crs":"TAU","via":null}],"destination":[{"locationName":"Cardiff Central","crs":"CDF","via":null}],"journeyDetails":{"from":{"locationName":"Taunton","crs":"TAU","via":null},"to":{"locationName":"Cardiff Central","crs":"CDF","via":null},"stops":15,"departureInfo":{"scheduled":"2025-02-24T08:19:00+00:00","estimated":null,"actual":"2025-02-24T08:21:57+00:00"},"arrivalInfo":{"scheduled":"2025-02-24T10:16:00+00:00","estimated":"2025-02-24T10:23:23+00:00","actual":null}},"operator":{"name":"Great Western Railway","code":"GW"},"status":{"status":"Late","delayReason":null,"cancelReason":null},"departureInfo":null,"arrivalInfo":{"scheduled":"2025-02-24T10:16:00+00:00","estimated":"2025-02-24T10:23:23+00:00","actual":null},"platform":"4","loadingLevel":"Unknown"},{"rid":"202502248719964","trainUid":"W19964","serviceType":{"mode":"Train","category":"PassengerTrain"},"origin":[{"locationName":"Barry Island","crs":"BYI","via":null}],"destination":[{"locationName":"Bargoed","crs":"BGD","via":null}],"journeyDetails":{"from":{"locationName":"Barry Island","crs":"BYI","via":null},"to":{"locationName":"Cardiff Central","crs":"CDF","via":null},"stops":8,"departureInfo":{"scheduled":"2025-02-24T09:49:00+00:00","estimated":null,"actual":"2025-02-24T09:49:12+00:00"},"arrivalInfo":{"scheduled":"2025-02-24T10:21:00+00:00","estimated":null,"actual":"2025-02-24T10:19:41+00:00"}},"operator":{"name":"Transport for Wales","code":"AW"},"status":{"status":"OnTime","delayReason":null,"cancelReason":null},"departureInfo":{"scheduled":"2025-02-24T10:22:00+00:00","estimated":null,"actual":"2025-02-24T10:22:10+00:00"},"arrivalInfo":{"scheduled":"2025-02-24T10:21:00+00:00","estimated":null,"actual":"2025-02-24T10:19:41+00:00"},"platform":"6","loadingLevel":"Unknown"},{"rid":"202502248717870","trainUid":"W17870","serviceType":{"mode":"Train","category":"ExpressPassengerTrain"},"origin":[{"locationName":"Aberdare","crs":"ABA","via":null}],"destination":[{"locationName":"Merthyr Tydfil","crs":"MER","via":null}],"journeyDetails":{"from":{"locationName":"Aberdare","crs":"ABA","via":null},"to":{"locationName":"Cardiff Central","crs":"CDF","via":null},"stops":14,"departureInfo":{"scheduled":"2025-02-24T09:21:00+00:00","estimated":null,"actual":"2025-02-24T09:21:09+00:00"},"arrivalInfo":{"scheduled":"2025-02-24T10:22:00+00:00","estimated":null,"actual":"2025-02-24T10:21:23+00:00"}},"operator":{"name":"Transport for Wales","code":"AW"},"status":{"status":"OnTime","delayReason":"This train has been delayed by heavy rain flooding the railway","cancelReason":null},"departureInfo":{"scheduled":"2025-02-24T10:26:00+00:00","estimated":null,"actual":null},"arrivalInfo":{"scheduled":"2025-02-24T10:22:00+00:00","estimated":null,"actual":"2025-02-24T10:21:23+00:00"},"platform":"7","loadingLevel":"Unknown"},{"rid":"202502248011991","trainUid":"P11991","serviceType":{"mode":"Train","category":"ExpressPassengerTrain"},"origin":[{"locationName":"Nottingham","crs":"NOT","via":null}],"destination":[{"locationName":"Cardiff Central","crs":"CDF","via":null}],"journeyDetails":{"from":{"locationName":"Nottingham","crs":"NOT","via":null},"to":{"locationName":"Cardiff Central","crs":"CDF","via":null},"stops":16,"departureInfo":{"scheduled":"2025-02-24T07:04:00+00:00","estimated":null,"actual":"2025-02-24T07:04:07+00:00"},"arrivalInfo":{"scheduled":"2025-02-24T10:25:00+00:00","estimated":"2025-02-24T10:28:35+00:00","actual":null}},"operator":{"name":"CrossCountry","code":"XC"},"status":{"status":"Late","delayReason":null,"cancelReason":null},"departureInfo":null,"arrivalInfo":{"scheduled":"2025-02-24T10:25:00+00:00","estimated":"2025-02-24T10:28:35+00:00","actual":null},"platform":"2","loadingLevel":"Unknown"},{"rid":"202502248717343","trainUid":"W17343","serviceType":{"mode":"Train","category":"PassengerTrain"},"origin":[{"locationName":"Bargoed","crs":"BGD","via":null}],"destination":[{"locationName":"Barry Island","crs":"BYI","via":null}],"journeyDetails":{"from":{"locationName":"Bargoed","crs":"BGD","via":null},"to":{"locationName":"Cardiff Central","crs":"CDF","via":null},"stops":12,"departureInfo":{"scheduled":"2025-02-24T09:43:00+00:00","estimated":null,"actual":"2025-02-24T09:48:35+00:00"},"arrivalInfo":{"scheduled":"2025-02-24T10:28:00+00:00","estimated":"2025-02-24T10:32:35+00:00","actual":null}},"operator":{"name":"Transport for Wales","code":"AW"},"status":{"status":"Late","delayReason":"This train has been delayed by a fault on this train","cancelReason":null},"departureInfo":{"scheduled":"2025-02-24T10:29:00+00:00","estimated":"2025-02-24T10:33:35+00:00","actual":null},"arrivalInfo":{"scheduled":"2025-02-24T10:28:00+00:00","estimated":"2025-02-24T10:32:35+00:00","actual":null},"platform":"8","loadingLevel":"Unknown"},{"rid":"202502248720570","trainUid":"W20570","serviceType":{"mode":"Train","category":"PassengerTrain"},"origin":[{"locationName":"Pembroke Dock","crs":"PMD","via":null}],"destination":[{"locationName":"Cardiff Central","crs":"CDF","via":null}],"journeyDetails":{"from":{"locationName":"Pembroke Dock","crs":"PMD","via":null},"to":{"locationName":"Cardiff Central","crs":"CDF","via":null},"stops":28,"departureInfo":{"scheduled":"2025-02-24T07:07:00+00:00","estimated":null,"actual":"2025-02-24T07:07:00+00:00"},"arrivalInfo":{"scheduled":"2025-02-24T10:37:00+00:00","estimated":"2025-02-24T10:37:00+00:00","actual":null}},"operator":{"name":"Transport for Wales","code":"AW"},"status":{"status":"OnTime","delayReason":null,"cancelReason":null},"departureInfo":null,"arrivalInfo":{"scheduled":"2025-02-24T10:37:00+00:00","estimated":"2025-02-24T10:37:00+00:00","actual":null},"platform":"0","loadingLevel":"Unknown"},{"rid":"202502248719868","trainUid":"W19868","serviceType":{"mode":"Train","category":"PassengerTrain"},"origin":[{"locationName":"Rhymney","crs":"RHY","via":null}],"destination":[{"locationName":"Bridgend","crs":"BGN","via":"via Rhoose Cardiff Int Airport"}],"journeyDetails":{"from":{"locationName":"Rhymney","crs":"RHY","via":null},"to":{"locationName":"Cardiff Central","crs":"CDF","via":null},"stops":12,"departureInfo":{"scheduled":"2025-02-24T09:44:00+00:00","estimated":null,"actual":"2025-02-24T09:44:12+00:00"},"arrivalInfo":{"scheduled":"2025-02-24T10:37:00+00:00","estimated":"2025-02-24T10:37:32+00:00","actual":null}},"operator":{"name":"Transport for Wales","code":"AW"},"status":{"status":"OnTime","delayReason":null,"cancelReason":null},"departureInfo":{"scheduled":"2025-02-24T10:38:00+00:00","estimated":"2025-02-24T10:38:00+00:00","actual":null},"arrivalInfo":{"scheduled":"2025-02-24T10:37:00+00:00","estimated":"2025-02-24T10:37:32+00:00","actual":null},"platform":"8","loadingLevel":"Unknown"},{"rid":"202502248921963","trainUid":"Y21963","serviceType":{"mode":"Train","category":"ExpressPassengerTrain"},"origin":[{"locationName":"London Paddington","crs":"PAD","via":null}],"destination":[{"locationName":"Swansea","crs":"SWA","via":null}],"journeyDetails":{"from":{"locationName":"London Paddington","crs":"PAD","via":null},"to":{"locationName":"Cardiff Central","crs":"CDF","via":null},"stops":5,"departureInfo":{"scheduled":"2025-02-24T08:48:00+00:00","estimated":null,"actual":"2025-02-24T08:48:05+00:00"},"arrivalInfo":{"scheduled":"2025-02-24T10:37:00+00:00","estimated":"2025-02-24T10:37:00+00:00","actual":null}},"operator":{"name":"Great Western Railway","code":"GW"},"status":{"status":"OnTime","delayReason":null,"cancelReason":null},"departureInfo":{"scheduled":"2025-02-24T10:39:00+00:00","estimated":"2025-02-24T10:39:00+00:00","actual":null},"arrivalInfo":{"scheduled":"2025-02-24T10:37:00+00:00","estimated":"2025-02-24T10:37:00+00:00","actual":null},"platform":"3","loadingLevel":"Unknown"},{"rid":"202502248719647","trainUid":"W19647","serviceType":{"mode":"Train","category":"PassengerTrain"},"origin":[{"locationName":"Bridgend","crs":"BGN","via":null}],"destination":[{"locationName":"Rhymney","crs":"RHY","via":null}],"journeyDetails":{"from":{"locationName":"Bridgend","crs":"BGN","via":null},"to":{"locationName":"Cardiff Central","crs":"CDF","via":null},"stops":10,"departureInfo":{"scheduled":"2025-02-24T09:40:00+00:00","estimated":null,"actual":null},"arrivalInfo":{"scheduled":"2025-02-24T10:40:00+00:00","estimated":"2025-02-24T10:40:00+00:00","actual":null}},"operator":{"name":"Transport for Wales","code":"AW"},"status":{"status":"OnTime","delayReason":null,"cancelReason":null},"departureInfo":{"scheduled":"2025-02-24T10:40:00+00:00","estimated":"2025-02-24T10:40:00+00:00","actual":null},"arrivalInfo":{"scheduled":"2025-02-24T10:40:00+00:00","estimated":"2025-02-24T10:40:00+00:00","actual":null},"platform":"6","loadingLevel":"Unknown"},{"rid":"202502248717955","trainUid":"W17955","serviceType":{"mode":"Train","category":"ExpressPassengerTrain"},"origin":[{"locationName":"Merthyr Tydfil","crs":"MER","via":null}],"destination":[{"locationName":"Aberdare","crs":"ABA","via":null}],"journeyDetails":{"from":{"locationName":"Merthyr Tydfil","crs":"MER","via":null},"to":{"locationName":"Cardiff Central","crs":"CDF","via":null},"stops":14,"departureInfo":{"scheduled":"2025-02-24T09:38:00+00:00","estimated":null,"actual":"2025-02-24T09:38:15+00:00"},"arrivalInfo":{"scheduled":"2025-02-24T10:40:00+00:00","estimated":"2025-02-24T10:40:00+00:00","actual":null}},"operator":{"name":"Transport for Wales","code":"AW"},"status":{"status":"OnTime","delayReason":"This train has been delayed by heavy rain flooding the railway","cancelReason":null},"departureInfo":{"scheduled":"2025-02-24T10:44:00+00:00","estimated":"2025-02-24T10:44:00+00:00","actual":null},"arrivalInfo":{"scheduled":"2025-02-24T10:40:00+00:00","estimated":"2025-02-24T10:40:00+00:00","actual":null},"platform":"7","loadingLevel":"Unknown"}]}}}
