{"data":{"ArrivalBoard":{"generatedAt":"2025-10-18T21:23:19.9099025+01:00","nrccMessages":[{"message":"The lifts are out of order between platforms 3 &amp; 4 and the subway at Cardiff Central station. Step free access is available via the west end lifts.","severity":"Normal"},{"message":"Trains running between Kings Norton and Redditch / Bromsgrove may be delayed by up to 20 minutes or revised. Latest information can be found in <a href=\"https://www.nationalrail.co.uk/service-disruptions/barnt-green-20251018/\">Status and Disruptions.</a>","severity":"Minor"}],"departureStation":{"locationName":"Cardiff Central","crs":"CDF","via":null},"filterStation":null,"services":[{"rid":"202510187104980","trainUid":"G04980","serviceType":{"mode":"Train","category":"ExpressPassengerTrain"},"origin":[{"locationName":"Swansea","crs":"SWA","via":null}],"destination":[{"locationName":"Bristol Parkway","crs":"BPW","via":null}],"journeyDetails":{"from":{"locationName":"Swansea","crs":"SWA","via":null},"to":{"locationName":"Cardiff Central","crs":"CDF","via":null},"stops":4,"departureInfo":{"scheduled":"2025-10-18T20:22:00+01:00","estimated":null,"actual":"2025-10-18T20:22:06+01:00"},"arrivalInfo":{"scheduled":"2025-10-18T21:15:00+01:00","estimated":null,"actual":"2025-10-18T21:21:51+01:00"}},"operator":{"name":"Great Western Railway","code":"GW"},"status":{"status":"Late","delayReason":null,"cancelReason":null},"departureInfo":{"scheduled":"2025-10-18T21:18:00+01:00","estimated":"2025-10-18T21:23:00+01:00","actual":null},"arrivalInfo":{"scheduled":"2025-10-18T21:15:00+01:00","estimated":null,"actual":"2025-10-18T21:21:51+01:00"},"platform":"1","loadingLevel":"Unknown"},{"rid":"202510187156029","trainUid":"G56029","serviceType":{"mode":"Train","category":"ExpressPassengerTrain"},"origin":[{"locationName":"Holyhead","crs":"HHD","via":null}],"destination":[{"locationName":"Cardiff Central","crs":"CDF","via":null}],"journeyDetails":{"from":{"locationName":"Holyhead","crs":"HHD","via":null},"to":{"locationName":"Cardiff Central","crs":"CDF","via":null},"stops":24,"departureInfo":{"scheduled":"2025-10-18T16:29:00+01:00","estimated":null,"actual":"2025-10-18T16:29:00+01:00"},"arrivalInfo":{"scheduled":"2025-10-18T21:22:00+01:00","estimated":null,"actual":"2025-10-18T21:21:32+01:00"}},"operator":{"name":"Transport for Wales","code":"AW"},"status":{"status":"OnTime","delayReason":null,"cancelReason":null},"departureInfo":null,"arrivalInfo":{"scheduled":"2025-10-18T21:22:00+01:00","estimated":null,"actual":"2025-10-18T21:21:32+01:00"},"platform":"3B","loadingLevel":"Unknown"},{"rid":"202510188643345","trainUid":"V43345","serviceType":{"mode":"Train","category":"PassengerTrain"},"origin":[{"locationName":"Aberdare","crs":"ABA","via":null}],"destination":[{"locationName":"Cardiff Central","crs":"CDF","via":null}],"journeyDetails":{"from":{"locationName":"Aberdare","crs":"ABA","via":null},"to":{"locationName":"Cardiff Central","crs":"CDF","via":null},"stops":14,"departureInfo":{"scheduled":"2025-10-18T20:22:00+01:00","estimated":null,"actual":"2025-10-18T20:22:29+01:00"},"arrivalInfo":{"scheduled":"2025-10-18T21:24:00+01:00","estimated":null,"actual":"2025-10-18T21:22:55+01:00"}},"operator":{"name":"Transport for Wales","code":"AW"},"status":{"status":"OnTime","delayReason":null,"cancelReason":null},"departureInfo":null,"arrivalInfo":{"scheduled":"2025-10-18T21:24:00+01:00","estimated":null,"actual":"2025-10-18T21:22:55+01:00"},"platform":"6","loadingLevel":"Unknown"},{"rid":"202510187157636","trainUid":"G57636","serviceType":{"mode":"Train","category":"PassengerTrain"},"origin":[{"locationName":"Coryton","crs":"COY","via":null}],"destination":[{"locationName":"Penarth","crs":"PEN","via":null}],"journeyDetails":{"from":{"locationName":"Coryton","crs":"COY","via":null},"to":{"locationName":"Cardiff Central","crs":"CDF","via":null},"stops":6,"departureInfo":{"scheduled":"2025-10-18T21:12:00+01:00","estimated":null,"actual":"2025-10-18T21:12:00+01:00"},"arrivalInfo":{"scheduled":"2025-10-18T21:33:00+01:00","estimated":"2025-10-18T21:33:00+01:00","actual":null}},"operator":{"name":"Transport for Wales","code":"AW"},"status":{"status":"OnTime","delayReason":null,"cancelReason":null},"departureInfo":{"scheduled":"2025-10-18T21:35:00+01:00","estimated":"2025-10-18T21:35:00+01:00","actual":null},"arrivalInfo":{"scheduled":"2025-10-18T21:33:00+01:00","estimated":"2025-10-18T21:33:00+01:00","actual":null},"platform":"8","loadingLevel":"Unknown"},{"rid":"202510187104783","trainUid":"G04783","serviceType":{"mode":"Train","category":"ExpressPassengerTrain"},"origin":[{"locationName":"London Paddington","crs":"PAD","via":null}],"destination":[{"locationName":"Swansea","crs":"SWA","via":null}],"journeyDetails":{"from":{"locationName":"London Paddington","crs":"PAD","via":null},"to":{"locationName":"Cardiff Central","crs":"CDF","via":null},"stops":5,"departureInfo":{"scheduled":"2025-10-18T19:48:00+01:00","estimated":null,"actual":"2025-10-18T19:58:19+01:00"},"arrivalInfo":{"scheduled":"2025-10-18T21:36:00+01:00","estimated":"2025-10-18T21:52:27+01:00","actual":null}},"operator":{"name":"Great Western Railway","code":"GW"},"status":{"status":"Late","delayReason":"This train has been delayed by a late running train being in front of this one","cancelReason":null},"departureInfo":{"scheduled":"2025-10-18T21:40:00+01:00","estimated":"2025-10-18T21:53:27+01:00","actual":null},"arrivalInfo":{"scheduled":"2025-10-18T21:36:00+01:00","estimated":"2025-10-18T21:52:27+01:00","actual":null},"platform":"3","loadingLevel":"Unknown"},{"rid":"202510188643376","trainUid":"V43376","serviceType":{"mode":"Train","category":"PassengerTrain"},"origin":[{"locationName":"Ninian Park","crs":"NNP","via":null}],"destination":[{"locationName":"Aberdare Platform 2","crs":"XCB","via":null}],"journeyDetails":{"from":{"locationName":"Ninian Park","crs":"NNP","via":null},"to":{"locationName":"Cardiff Central","crs":"CDF","via":null},"stops":1,"departureInfo":{"scheduled":"2025-10-18T21:32:00+01:00","estimated":"2025-10-18T21:32:00+01:00","actual":null},"arrivalInfo":{"scheduled":"2025-10-18T21:37:00+01:00","estimated":"2025-10-18T21:37:00+01:00","actual":null}},"operator":{"name":"Transport for Wales","code":"AW"},"status":{"status":"OnTime","delayReason":null,"cancelReason":null},"departureInfo":{"scheduled":"2025-10-18T21:37:00+01:00","estimated":"2025-10-18T21:37:00+01:00","actual":null},"arrivalInfo":{"scheduled":"2025-10-18T21:37:00+01:00","estimated":"2025-10-18T21:37:00+01:00","actual":null},"platform":"6","loadingLevel":"Unknown"},{"rid":"202510187156767","trainUid":"G56767","serviceType":{"mode":"Train","category":"PassengerTrain"},"origin":[{"locationName":"Caerphilly","crs":"CPH","via":null}],"destination":[{"locationName":"Bridgend","crs":"BGN","via":"via Rhoose Cardiff Int Airport"}],"journeyDetails":{"from":{"locationName":"Caerphilly","crs":"CPH","via":null},"to":{"locationName":"Cardiff Central","crs":"CDF","via":null},"stops":5,"departureInfo":{"scheduled":"2025-10-18T21:18:00+01:00","estimated":null,"actual":"2025-10-18T21:19:03+01:00"},"arrivalInfo":{"scheduled":"2025-10-18T21:38:00+01:00","estimated":"2025-10-18T21:38:00+01:00","actual":null}},"operator":{"name":"Transport for Wales","code":"AW"},"status":{"status":"OnTime","delayReason":null,"cancelReason":null},"departureInfo":{"scheduled":"2025-10-18T21:39:00+01:00","estimated":"2025-10-18T21:39:00+01:00","actual":null},"arrivalInfo":{"scheduled":"2025-10-18T21:38:00+01:00","estimated":"2025-10-18T21:38:00+01:00","actual":null},"platform":"8","loadingLevel":"Unknown"},{"rid":"202510187157811","trainUid":"G57811","serviceType":{"mode":"Train","category":"PassengerTrain"},"origin":[{"locationName":"Bridgend","crs":"BGN","via":null}],"destination":[{"locationName":"Caerphilly","crs":"CPH","via":null}],"journeyDetails":{"from":{"locationName":"Bridgend","crs":"BGN","via":null},"to":{"locationName":"Cardiff Central","crs":"CDF","via":null},"stops":10,"departureInfo":{"scheduled":"2025-10-18T20:40:00+01:00","estimated":null,"actual":"2025-10-18T20:39:17+01:00"},"arrivalInfo":{"scheduled":"2025-10-18T21:41:00+01:00","estimated":"2025-10-18T21:41:00+01:00","actual":null}},"operator":{"name":"Transport for Wales","code":"AW"},"status":{"status":"OnTime","delayReason":null,"cancelReason":null},"departureInfo":{"scheduled":"2025-10-18T21:41:00+01:00","estimated":"2025-10-18T21:41:00+01:00","actual":null},"arrivalInfo":{"scheduled":"2025-10-18T21:41:00+01:00","estimated":"2025-10-18T21:41:00+01:00","actual":null},"platform":"6","loadingLevel":"Unknown"},{"rid":"202510188643422","trainUid":"V43422","serviceType":{"mode":"Train","category":"ExpressPassengerTrain"},"origin":[{"locationName":"Merthyr Tydfil","crs":"MER","via":null}],"destination":[{"locationName":"Ninian Park","crs":"NNP","via":null}],"journeyDetails":{"from":{"locationName":"Merthyr Tydfil","crs":"MER","via":null},"to":{"locationName":"Cardiff Central","crs":"CDF","via":null},"stops":14,"departureInfo":{"scheduled":"2025-10-18T20:39:00+01:00","estimated":null,"actual":"2025-10-18T20:39:46+01:00"},"arrivalInfo":{"scheduled":"2025-10-18T21:42:00+01:00","estimated":"2025-10-18T21:42:00+01:00","actual":null}},"operator":{"name":"Transport for Wales","code":"AW"},"status":{"status":"OnTime","delayReason":null,"cancelReason":null},"departureInfo":{"scheduled":"2025-10-18T21:43:00+01:00","estimated":"2025-10-18T21:43:00+01:00","actual":null},"arrivalInfo":{"scheduled":"2025-10-18T21:42:00+01:00","estimated":"2025-10-18T21:42:00+01:00","actual":null},"platform":"7","loadingLevel":"Unknown"},{"rid":"202510187104910","trainUid":"G04910","serviceType":{"mode":"Train","category":"ExpressPassengerTrain"},"origin":[{"locationName":"Portsmouth Harbour","crs":"PMH","via":null}],"destination":[{"locationName":"Cardiff Central","crs":"CDF","via":null}],"journeyDetails":{"from":{"locationName":"Portsmouth Harbour","crs":"PMH","via":null},"to":{"locationName":"Cardiff Central","crs":"CDF","via":null},"stops":17,"departureInfo":{"scheduled":"2025-10-18T18:23:00+01:00","estimated":null,"actual":"2025-10-18T18:23:20+01:00"},"arrivalInfo":{"scheduled":"2025-10-18T21:45:00+01:00","estimated":"2025-10-18T21:45:00+01:00","actual":null}},"operator":{"name":"Great Western Railway","code":"GW"},"status":{"status":"OnTime","delayReason":null,"cancelReason":null},"departureInfo":null,"arrivalInfo":{"scheduled":"2025-10-18T21:45:00+01:00","estimated":"2025-10-18T21:45:00+01:00","actual":null},"platform":"1","loadingLevel":"Unknown"}]}}}
