{"data":{"ArrivalBoard":{"generatedAt":"2025-11-22T20:25:42.9021021+00:00","nrccMessages":[{"message":"Buses replace trains between Whitland and Pembroke Dock. Latest information can be found in <a href=\"https://www.nationalrail.co.uk/service-disruptions/pembroke-dock-20251122/\">Status and Disruptions</a>.","severity":"Minor"},{"message":"Trains running between Bristol Parkway / Filton Abbey Wood and Severn Tunnel Junction may be delayed by up to 30 minutes or revised. Latest information can be found in <a href=\"https://www.nationalrail.co.uk/service-disruptions/patchway-20251122/\">Status and Disruptions.</a>","severity":"Minor"}],"departureStation":{"locationName":"Cardiff Central","crs":"CDF","via":null},"filterStation":null,"services":[{"rid":"202511227104779","trainUid":"G04779","serviceType":{"mode":"Train","category":"ExpressPassengerTrain"},"origin":[{"locationName":"London Paddington","crs":"PAD","via":null}],"destination":[{"locationName":"Swansea","crs":"SWA","via":null}],"journeyDetails":{"from":{"locationName":"London Paddington","crs":"PAD","via":null},"to":{"locationName":"Cardiff Central","crs":"CDF","via":null},"stops":5,"departureInfo":{"scheduled":"2025-11-22T17:48:00+00:00","estimated":null,"actual":"2025-11-22T17:51:46+00:00"},"arrivalInfo":{"scheduled":"2025-11-22T19:37:00+00:00","estimated":null,"actual":"2025-11-22T20:21:08+00:00"}},"operator":{"name":"Great Western Railway","code":"GW"},"status":{"status":"Late","delayReason":"a points failure","cancelReason":null},"departureInfo":{"scheduled":"2025-11-22T19:40:00+00:00","estimated":"2025-11-22T20:25:00+00:00","actual":null},"arrivalInfo":{"scheduled":"2025-11-22T19:37:00+00:00","estimated":null,"actual":"2025-11-22T20:21:08+00:00"},"platform":"3","loadingLevel":"Unknown"},{"rid":"202511227104780","trainUid":"G04780","serviceType":{"mode":"Train","category":"ExpressPassengerTrain"},"origin":[{"locationName":"London Paddington","crs":"PAD","via":null}],"destination":[{"locationName":"Swansea","crs":"SWA","via":null}],"journeyDetails":{"from":{"locationName":"London Paddington","crs":"PAD","via":null},"to":{"locationName":"Cardiff Central","crs":"CDF","via":null},"stops":6,"departureInfo":{"scheduled":"2025-11-22T18:18:00+00:00","estimated":null,"actual":"2025-11-22T18:19:39+00:00"},"arrivalInfo":{"scheduled":"2025-11-22T20:10:00+00:00","estimated":null,"actual":null}},"operator":{"name":"Great Western Railway","code":"GW"},"status":{"status":"Delayed","delayReason":"a points failure","cancelReason":null},"departureInfo":{"scheduled":"2025-11-22T20:12:00+00:00","estimated":null,"actual":null},"arrivalInfo":{"scheduled":"2025-11-22T20:10:00+00:00","estimated":null,"actual":null},"platform":"4","loadingLevel":"Unknown"},{"rid":"202511227157585","trainUid":"G57585","serviceType":{"mode":"Train","category":"PassengerTrain"},"origin":[{"locationName":"Ebbw Vale Town","crs":"EBB","via":null}],"destination":[{"locationName":"Maesteg","crs":"MST","via":null}],"journeyDetails":{"from":{"locationName":"Ebbw Vale Town","crs":"EBB","via":null},"to":{"locationName":"Cardiff Central","crs":"CDF","via":null},"stops":9,"departureInfo":{"scheduled":"2025-11-22T19:07:00+00:00","estimated":null,"actual":"2025-11-22T19:22:00+00:00"},"arrivalInfo":{"scheduled":"2025-11-22T20:14:00+00:00","estimated":"2025-11-22T20:25:30+00:00","actual":null}},"operator":{"name":"Transport for Wales","code":"AW"},"status":{"status":"Late","delayReason":"the train departing late to maintain customer connections","cancelReason":null},"departureInfo":{"scheduled":"2025-11-22T20:17:00+00:00","estimated":"2025-11-22T20:26:30+00:00","actual":null},"arrivalInfo":{"scheduled":"2025-11-22T20:14:00+00:00","estimated":"2025-11-22T20:25:30+00:00","actual":null},"platform":"3A","loadingLevel":"Unknown"},{"rid":"202511227156930","trainUid":"G56930","serviceType":{"mode":"Train","category":"PassengerTrain"},"origin":[{"locationName":"Treherbert","crs":"TRB","via":null}],"destination":[{"locationName":"Cardiff Central","crs":"CDF","via":null}],"journeyDetails":{"from":{"locationName":"Treherbert","crs":"TRB","via":null},"to":{"locationName":"Cardiff Central","crs":"CDF","via":null},"stops":17,"departureInfo":{"scheduled":"2025-11-22T19:10:00+00:00","estimated":null,"actual":"2025-11-22T19:13:34+00:00"},"arrivalInfo":{"scheduled":"2025-11-22T20:16:00+00:00","estimated":"2025-11-22T20:26:30+00:00","actual":null}},"operator":{"name":"Transport for Wales","code":"AW"},"status":{"status":"Late","delayReason":"overcrowding because of a rugby match","cancelReason":null},"departureInfo":null,"arrivalInfo":{"scheduled":"2025-11-22T20:16:00+00:00","estimated":"2025-11-22T20:26:30+00:00","actual":null},"platform":"7","loadingLevel":"Unknown"},{"rid":"202511227104979","trainUid":"G04979","serviceType":{"mode":"Train","category":"ExpressPassengerTrain"},"origin":[{"locationName":"Swansea","crs":"SWA","via":null}],"destination":[{"locationName":"London Paddington","crs":"PAD","via":null}],"journeyDetails":{"from":{"locationName":"Swansea","crs":"SWA","via":null},"to":{"locationName":"Cardiff Central","crs":"CDF","via":null},"stops":4,"departureInfo":{"scheduled":"2025-11-22T19:22:00+00:00","estimated":null,"actual":"2025-11-22T20:17:15+00:00"},"arrivalInfo":{"scheduled":"2025-11-22T20:16:00+00:00","estimated":"2025-11-22T21:07:29+00:00","actual":null}},"operator":{"name":"Great Western Railway","code":"GW"},"status":{"status":"Late","delayReason":"a points failure","cancelReason":null},"departureInfo":{"scheduled":"2025-11-22T20:22:00+00:00","estimated":"2025-11-22T21:08:29+00:00","actual":null},"arrivalInfo":{"scheduled":"2025-11-22T20:16:00+00:00","estimated":"2025-11-22T21:07:29+00:00","actual":null},"platform":"1","loadingLevel":"Unknown"},{"rid":"202511227156466","trainUid":"G56466","serviceType":{"mode":"Train","category":"PassengerTrain"},"origin":[{"locationName":"Penarth","crs":"PEN","via":null}],"destination":[{"locationName":"Coryton","crs":"COY","via":null}],"journeyDetails":{"from":{"locationName":"Penarth","crs":"PEN","via":null},"to":{"locationName":"Cardiff Central","crs":"CDF","via":null},"stops":3,"departureInfo":{"scheduled":"2025-11-22T20:05:00+00:00","estimated":null,"actual":null},"arrivalInfo":{"scheduled":"2025-11-22T20:17:00+00:00","estimated":null,"actual":null}},"operator":{"name":"Transport for Wales","code":"AW"},"status":{"status":"Cancelled","delayReason":null,"cancelReason":"trespassers on the railway earlier today"},"departureInfo":null,"arrivalInfo":{"scheduled":"2025-11-22T20:17:00+00:00","estimated":null,"actual":null},"platform":"7B","loadingLevel":"Unknown"},{"rid":"202511227156937","trainUid":"G56937","serviceType":{"mode":"Train","category":"PassengerTrain"},"origin":[{"locationName":"Barry Island","crs":"BYI","via":null}],"destination":[{"locationName":"Cardiff Central","crs":"CDF","via":null}],"journeyDetails":{"from":{"locationName":"Barry Island","crs":"BYI","via":null},"to":{"locationName":"Cardiff Central","crs":"CDF","via":null},"stops":8,"departureInfo":{"scheduled":"2025-11-22T19:49:00+00:00","estimated":null,"actual":"2025-11-22T19:52:26+00:00"},"arrivalInfo":{"scheduled":"2025-11-22T20:21:00+00:00","estimated":"2025-11-22T20:26:00+00:00","actual":null}},"operator":{"name":"Transport for Wales","code":"AW"},"status":{"status":"Late","delayReason":null,"cancelReason":null},"departureInfo":null,"arrivalInfo":{"scheduled":"2025-11-22T20:21:00+00:00","estimated":"2025-11-22T20:26:00+00:00","actual":null},"platform":"7","loadingLevel":"Unknown"},{"rid":"202511226723720","trainUid":"C23720","serviceType":{"mode":"Train","category":"ExpressPassengerTrain"},"origin":[{"locationName":"Nottingham","crs":"NOT","via":null}],"destination":[{"locationName":"Cardiff Central","crs":"CDF","via":null}],"journeyDetails":{"from":{"locationName":"Nottingham","crs":"NOT","via":null},"to":{"locationName":"Cardiff Central","crs":"CDF","via":null},"stops":12,"departureInfo":{"scheduled":"2025-11-22T17:07:00+00:00","estimated":"2025-11-22T17:07:00+00:00","actual":null},"arrivalInfo":{"scheduled":"2025-11-22T20:22:00+00:00","estimated":null,"actual":null}},"operator":{"name":"CrossCountry","code":"XC"},"status":{"status":"Cancelled","delayReason":null,"cancelReason":"a shortage of train drivers"},"departureInfo":null,"arrivalInfo":{"scheduled":"2025-11-22T20:22:00+00:00","estimated":null,"actual":null},"platform":"3","loadingLevel":"Unknown"},{"rid":"202511227155912","trainUid":"G55912","serviceType":{"mode":"Train","category":"ExpressPassengerTrain"},"origin":[{"locationName":"Aberdare","crs":"ABA","via":null}],"destination":[{"locationName":"Cardiff Central","crs":"CDF","via":null}],"journeyDetails":{"from":{"locationName":"Aberdare","crs":"ABA","via":null},"to":{"locationName":"Cardiff Central","crs":"CDF","via":null},"stops":15,"departureInfo":{"scheduled":"2025-11-22T19:22:00+00:00","estimated":null,"actual":"2025-11-22T19:28:08+00:00"},"arrivalInfo":{"scheduled":"2025-11-22T20:25:00+00:00","estimated":"2025-11-22T20:25:01+00:00","actual":null}},"operator":{"name":"Transport for Wales","code":"AW"},"status":{"status":"OnTime","delayReason":"overcrowding because of a rugby match","cancelReason":null},"departureInfo":null,"arrivalInfo":{"scheduled":"2025-11-22T20:25:00+00:00","estimated":"2025-11-22T20:25:01+00:00","actual":null},"platform":"6","loadingLevel":"Unknown"},{"rid":"202511227106178","trainUid":"G06178","serviceType":{"mode":"Train","category":"PassengerTrain"},"origin":[{"locationName":"Taunton","crs":"TAU","via":null}],"destination":[{"locationName":"Cardiff Central","crs":"CDF","via":null}],"journeyDetails":{"from":{"locationName":"Taunton","crs":"TAU","via":null},"to":{"locationName":"Cardiff Central","crs":"CDF","via":null},"stops":14,"departureInfo":{"scheduled":"2025-11-22T18:16:00+00:00","estimated":null,"actual":"2025-11-22T18:16:04+00:00"},"arrivalInfo":{"scheduled":"2025-11-22T20:27:00+00:00","estimated":"2025-11-22T20:43:36+00:00","actual":null}},"operator":{"name":"Great Western Railway","code":"GW"},"status":{"status":"Late","delayReason":"a points failure","cancelReason":null},"departureInfo":null,"arrivalInfo":{"scheduled":"2025-11-22T20:27:00+00:00","estimated":"2025-11-22T20:43:36+00:00","actual":null},"platform":"2","loadingLevel":"Unknown"}]}}}
